{"sections":{"main":{"type":"casa-contact-page","blocks":{"card_email":{"type":"contact_card","settings":{"icon":"mail","title":"Email","content":"<p>hello@seoulglow.com<\/p>"}},"card_phone":{"type":"contact_card","settings":{"icon":"phone","title":"Phone","content":"<p>+1 (404)-410-0199<br\/>MON-SAT 9am - 5pm EST<\/p>"}},"card_address":{"type":"contact_card","settings":{"icon":"location","title":"Casa Di Lumo LLC.","content":"<p>4225 JVL Industrial Park Dr<br\/>Building 2, Suite 204<br\/>Marietta, Georgia, 30066<br\/>United States<\/p>"}},"gorgias_form":{"type":"form_embed","settings":{"heading":"Send Us a Message","subheading":"Fill out the form below and our team will respond within 24 hours.","custom_liquid":"<div data-gorgias-contact-form-uid=\"sj8s4v1g\"><\/div><script defer src=\"https:\/\/contact.gorgias.help\/api\/contact-forms\/loader.js?v=2\" data-gorgias-loader-contact-form><\/script>"}},"sms_notice":{"type":"text_block","settings":{"heading":"SMS NOTICE","content":"<p>Text us at <strong>+1 (404)-410-0199<\/strong> to connect with Casa Di Lumo. By confirming, you consent to receive SMS messages. Message and data rates may apply. Reply HELP for support or STOP to opt out.<\/p>"}}},"block_order":["card_email","card_phone","card_address","gorgias_form","sms_notice"],"settings":{"badge_text":"Get In Touch","heading":"Contact Us","subheading":"We're here to help. Reach out to our team and we'll get back to you as soon as possible.","accent_purple":"#ffffff","accent_pink":"#ffffff","bg_color":"#000000","padding_top":80,"padding_bottom":80}}},"order":["main"]}